fscolor/__init__.py
fscolor/colors.py
fscolor-0.1.2.dist-info/licenses/LICENSE
fscolor-0.1.2.dist-info/METADATA
fscolor-0.1.2.dist-info/WHEEL
fscolor-0.1.2.dist-info/top_level.txt
fscolor-0.1.2.dist-info/RECORD
